__init__.py
qdiff/__init__.py
qdiff/__main__.py
qdiff/diff.py
qdiff/diff_arch.py
qdiff/diff_design.py
qdiff/diff_impl.py
qdiff/diff_test.py
qdiff/diff_testability.py
qdiff/qdiff.py
qdiff/smell_diff.py
qdiff/states.py
qdiff-1.0.1.dist-info/METADATA
qdiff-1.0.1.dist-info/WHEEL
qdiff-1.0.1.dist-info/entry_points.txt
qdiff-1.0.1.dist-info/top_level.txt
qdiff-1.0.1.dist-info/RECORD
