Metadata-Version: 2.4
Name: qdiff
Version: 1.0.1
Summary: Diff tool for code quality analysis reports
License: MPL-2.0
Classifier: Programming Language :: Python :: 3
Classifier: Programming Language :: Python :: 3 :: Only
Classifier: Operating System :: OS Independent
Requires-Python: >=3.9
